LICENSE.md
MANIFEST.in
README.md
pyproject.toml
setup.cfg
setup.py
openpyn/__init__.py
openpyn/__main__.py
openpyn/api.py
openpyn/asus.py
openpyn/converter.py
openpyn/credentials.py
openpyn/filters.py
openpyn/firewall.py
openpyn/initd.py
openpyn/locations.py
openpyn/openpyn.py
openpyn/root.py
openpyn/routes.py
openpyn/systemd.py
openpyn/management/management.py
openpyn/scripts/manual-dns-patch.sh
openpyn/scripts/revert-manual-dns-patch.sh
openpyn/scripts/update-resolv-conf.sh
openpyn/scripts/update-systemd-resolved.sh