Metadata-Version: 2.1
Name: openpyn
Version: 3.0.0
Summary: Easily connect to and switch between, OpenVPN servers hosted by NordVPN.
Home-page: https://github.com/jotyGill/openpyn-nordvpn/
Author: JGill
Author-email: joty@mygnu.org
License: GNU General Public License v3 or later (GPLv3+)
Keywords: openvpn wrapper,nordvpn,nordvpn client,secure vpn,vpn wrapper,private vpn,privacy
Platform: GNU/Linux
Platform: Ubuntu
Platform: Debian
Platform: Kali
Platform: CentOS
Platform: Arch
Platform: Fedora
Classifier: Intended Audience :: End Users/Desktop
Classifier: Intended Audience :: System Administrators
Classifier: Topic :: Utilities
Classifier: Topic :: Security
Classifier: License :: OSI Approved :: GNU General Public License v3 or later (GPLv3+)
Classifier: Natural Language :: English
Classifier: Operating System :: POSIX :: Linux
Classifier: Programming Language :: Python :: 3 :: Only
Classifier: Programming Language :: Python :: 3.5
Classifier: Programming Language :: Python :: 3.6
Classifier: Programming Language :: Python :: 3.7
Classifier: Programming Language :: Python :: 3.8
Classifier: Programming Language :: Python :: 3.9
Requires-Python: >=3.5
